ut_ctl/__init__.py
ut_ctl/__version__.py
ut_ctl/journalctl.py
ut_ctl/py.typed
ut_ctl/systemctl.py
ut_ctl-2.0.0.20251020.dist-info/licenses/LICENSE.txt
ut_ctl-2.0.0.20251020.dist-info/METADATA
ut_ctl-2.0.0.20251020.dist-info/WHEEL
ut_ctl-2.0.0.20251020.dist-info/entry_points.txt
ut_ctl-2.0.0.20251020.dist-info/top_level.txt
ut_ctl-2.0.0.20251020.dist-info/RECORD
